material_color_utilities_python/__init__.py
material_color_utilities_python/blend/__init__.py
material_color_utilities_python/blend/blend.py
material_color_utilities_python/hct/__init__.py
material_color_utilities_python/hct/cam16.py
material_color_utilities_python/hct/hct.py
material_color_utilities_python/hct/viewing_conditions.py
material_color_utilities_python/palettes/__init__.py
material_color_utilities_python/palettes/core_palette.py
material_color_utilities_python/palettes/tonal_palette.py
material_color_utilities_python/quantize/__init__.py
material_color_utilities_python/quantize/lab_point_provider.py
material_color_utilities_python/quantize/quantizer_celebi.py
material_color_utilities_python/quantize/quantizer_map.py
material_color_utilities_python/quantize/quantizer_wsmeans.py
material_color_utilities_python/quantize/quantizer_wu.py
material_color_utilities_python/scheme/__init__.py
material_color_utilities_python/scheme/scheme.py
material_color_utilities_python/score/__init__.py
material_color_utilities_python/score/score.py
material_color_utilities_python/utils/__init__.py
material_color_utilities_python/utils/color_utils.py
material_color_utilities_python/utils/image_utils.py
material_color_utilities_python/utils/math_utils.py
material_color_utilities_python/utils/string_utils.py
material_color_utilities_python/utils/theme_utils.py
material_color_utilities_python-0.1.4.dist-info/LICENSE.md
material_color_utilities_python-0.1.4.dist-info/WHEEL
material_color_utilities_python-0.1.4.dist-info/METADATA
material_color_utilities_python-0.1.4.dist-info/RECORD
