Metadata-Version: 2.1
Name: material-color-utilities-python
Version: 0.1.4
Summary: Python port of material-color-utilities used for Material You colors
License: Apache 2.0
Author: Avanish Subbiah
Author-email: avanishsubbiah1@gmail.com
Requires-Python: >=3.10,<4.0
Classifier: License :: Other/Proprietary License
Classifier: Programming Language :: Python :: 3
Classifier: Programming Language :: Python :: 3.10
Requires-Dist: Pillow (>=9.2.0,<10.0.0)
Requires-Dist: regex
